icstask.py
icstask-0.5.0.dist-info/LICENSE
icstask-0.5.0.dist-info/METADATA
icstask-0.5.0.dist-info/WHEEL
icstask-0.5.0.dist-info/entry_points.txt
icstask-0.5.0.dist-info/top_level.txt
icstask-0.5.0.dist-info/RECORD
