Metadata-Version: 2.1
Name: icstask
Version: 0.5.0
Summary: Python library to convert between Taskwarrior and vObject
Home-page: https://github.com/jspricke/python-icstask
Author: Jochen Sprickerhof
Author-email: taskwarrior@jochen.sprickerhof.de
License: GPLv3+
Keywords: Taskwarrior
Classifier: Programming Language :: Python
Classifier: Development Status :: 4 - Beta
Classifier: Environment :: Console
Classifier: License :: OSI Approved :: GNU General Public License v3 or later (GPLv3+)
Classifier: Topic :: Software Development :: Libraries :: Python Modules
License-File: LICENSE
Requires-Dist: vobject
